{
    "unified mentor":"charging registration fee",
    "labmentix":"charging registration fee",
    "skillFied mentor":"charging registration fee",
    "Be10X": "misleading & scam",
    "codetech it solutions private limited":"charging registration fee",
    "CodeAlpha":"charging registration fee",
    "ELEVATE LABS":"charging registration fee",
    "Zuaitech":"scam",
    "Winzons":"scam",
    "Winfrox":"scam",
    "Webcode":"scam",
    "skillcraft technology":"charging registration fee",
    "cognifyz technologies":"charging registration fee",
    "oasis infobyte":"charging fee for certification",
    "SkillInfytech IT Solutions Private Limited":"charging registration fee",
    "Infotact Solutions":"charging platform fee",
    "MedTourEasy":"charging registration fee",
    "Nullclass":"charging registration fee"
    "Mindshift Technologies": "charging registration fee",
    "SaiKet Systems":"charging registration fee",
    "Wiremetrics Solutions":"charging registration fee",
    "Zidio Development":"charging registration fee",
    "Wire Global Metrics":"charging registration fee",
    "Wire Cloud Metrics":"charging registration fee",
    "Nixona Technologies":"charging registration fee",
    "Pinnacle Labs":"charging registration fee",
    "qualcomm":"charging registration fee",
    "Encryptix":"scam",
    "CipherByte Technologies":"charging registration fee",
    "MindShift Interactive":"scam"
}











